{"nodes": [{"id": "api_doc_apex_legends_api", "label": "Apex Legends API Documentation", "file_type": "document", "source_file": "API_DOCUMENTATION.md", "source_location": null, "source_url": null, "captured_at": null, "author": null, "contributor": null}, {"id": "api_doc_base_url", "label": "Apex Legends API Base URL (api.mozambiquehe.re)", "file_type": "document", "source_file": "API_DOCUMENTATION.md", "source_location": "line 3", "source_url": "https://api.mozambiquehe.re", "captured_at": null, "author": null, "contributor": null}, {"id": "api_doc_provider_apexlegendsapi", "label": "API Provider: apexlegendsapi.com", "file_type": "document", "source_file": "API_DOCUMENTATION.md", "source_location": "line 4", "source_url": "https://apexlegendsapi.com", "captured_at": null, "author": null, "contributor": null}, {"id": "api_doc_proxy_server", "label": "Proxy Server (Express/Node)", "file_type": "document", "source_file": "API_DOCUMENTATION.md", "source_location": "line 9", "source_url": null, "captured_at": null, "author": null, "contributor": null}, {"id": "api_doc_endpoint_bridge", "label": "API Endpoint: /bridge (Player Stats)", "file_type": "document", "source_file": "API_DOCUMENTATION.md", "source_location": "line 63", "source_url": null, "captured_at": null, "author": null, "contributor": null}, {"id": "api_doc_endpoint_maprotation", "label": "API Endpoint: /maprotation (Map Rotation)", "file_type": "document", "source_file": "API_DOCUMENTATION.md", "source_location": "line 133", "source_url": null, "captured_at": null, "author": null, "contributor": null}, {"id": "api_doc_endpoint_servers", "label": "API Endpoint: /servers (Server Status)", "file_type": "document", "source_file": "API_DOCUMENTATION.md", "source_location": "line 199", "source_url": null, "captured_at": null, "author": null, "contributor": null}, {"id": "api_doc_endpoint_predator", "label": "API Endpoint: /predator (Predator Threshold)", "file_type": "document", "source_file": "API_DOCUMENTATION.md", "source_location": "line 449", "source_url": null, "captured_at": null, "author": null, "contributor": null}, {"id": "api_doc_endpoint_origin", "label": "API Endpoint: /origin (Player UID Lookup)", "file_type": "document", "source_file": "API_DOCUMENTATION.md", "source_location": "line 477", "source_url": null, "captured_at": null, "author": null, "contributor": null}, {"id": "api_doc_endpoint_nametouid", "label": "API Endpoint: /nametouid (Name to UID)", "file_type": "document", "source_file": "API_DOCUMENTATION.md", "source_location": "line 499", "source_url": null, "captured_at": null, "author": null, "contributor": null}, {"id": "api_doc_endpoint_news", "label": "API Endpoint: /news (News Feed)", "file_type": "document", "source_file": "API_DOCUMENTATION.md", "source_location": "line 549", "source_url": null, "captured_at": null, "author": null, "contributor": null}, {"id": "api_doc_endpoint_games", "label": "API Endpoint: /games (Match History)", "file_type": "document", "source_file": "API_DOCUMENTATION.md", "source_location": "line 591", "source_url": null, "captured_at": null, "author": null, "contributor": null}, {"id": "api_doc_platform_codes", "label": "Platform Codes (PC, PS4, X1, SWITCH)", "file_type": "document", "source_file": "API_DOCUMENTATION.md", "source_location": "line 39", "source_url": null, "captured_at": null, "author": null, "contributor": null}, {"id": "api_doc_rate_limiting", "label": "API Rate Limiting (1 req/2s default, 2 req/s with Discord)", "file_type": "document", "source_file": "API_DOCUMENTATION.md", "source_location": "line 54", "source_url": null, "captured_at": null, "author": null, "contributor": null}, {"id": "api_doc_client_token", "label": "Client Token Gate (x-client-token header)", "file_type": "document", "source_file": "API_DOCUMENTATION.md", "source_location": "line 11", "source_url": null, "captured_at": null, "author": null, "contributor": null}, {"id": "api_doc_attribution_apexlegendsstatus", "label": "Attribution Requirement: apexlegendsstatus.com", "file_type": "document", "source_file": "API_DOCUMENTATION.md", "source_location": "line 442", "source_url": "https://apexlegendsstatus.com", "captured_at": null, "author": null, "contributor": null}, {"id": "api_doc_error_codes", "label": "API Error Codes (400, 403, 404, 429, 500)", "file_type": "document", "source_file": "API_DOCUMENTATION.md", "source_location": "line 609", "source_url": null, "captured_at": null, "author": null, "contributor": null}], "edges": [{"source": "api_doc_apex_legends_api", "target": "api_doc_base_url", "relation": "references", "confidence": "EXTRACTED", "confidence_score": 1.0, "source_file": "API_DOCUMENTATION.md", "source_location": "line 3", "weight": 1.0}, {"source": "api_doc_apex_legends_api", "target": "api_doc_provider_apexlegendsapi", "relation": "references", "confidence": "EXTRACTED", "confidence_score": 1.0, "source_file": "API_DOCUMENTATION.md", "source_location": "line 4", "weight": 1.0}, {"source": "api_doc_proxy_server", "target": "api_doc_endpoint_bridge", "relation": "implements", "confidence": "EXTRACTED", "confidence_score": 1.0, "source_file": "API_DOCUMENTATION.md", "source_location": "line 17", "weight": 1.0}, {"source": "api_doc_proxy_server", "target": "api_doc_endpoint_maprotation", "relation": "implements", "confidence": "EXTRACTED", "confidence_score": 1.0, "source_file": "API_DOCUMENTATION.md", "source_location": "line 17", "weight": 1.0}, {"source": "api_doc_proxy_server", "target": "api_doc_endpoint_servers", "relation": "implements", "confidence": "EXTRACTED", "confidence_score": 1.0, "source_file": "API_DOCUMENTATION.md", "source_location": "line 17", "weight": 1.0}, {"source": "api_doc_proxy_server", "target": "api_doc_endpoint_predator", "relation": "implements", "confidence": "EXTRACTED", "confidence_score": 1.0, "source_file": "API_DOCUMENTATION.md", "source_location": "line 17", "weight": 1.0}, {"source": "api_doc_proxy_server", "target": "api_doc_endpoint_origin", "relation": "implements", "confidence": "EXTRACTED", "confidence_score": 1.0, "source_file": "API_DOCUMENTATION.md", "source_location": "line 17", "weight": 1.0}, {"source": "api_doc_proxy_server", "target": "api_doc_endpoint_nametouid", "relation": "implements", "confidence": "EXTRACTED", "confidence_score": 1.0, "source_file": "API_DOCUMENTATION.md", "source_location": "line 17", "weight": 1.0}, {"source": "api_doc_proxy_server", "target": "api_doc_endpoint_news", "relation": "implements", "confidence": "EXTRACTED", "confidence_score": 1.0, "source_file": "API_DOCUMENTATION.md", "source_location": "line 17", "weight": 1.0}, {"source": "api_doc_proxy_server", "target": "api_doc_endpoint_games", "relation": "implements", "confidence": "EXTRACTED", "confidence_score": 1.0, "source_file": "API_DOCUMENTATION.md", "source_location": "line 591", "weight": 1.0}, {"source": "api_doc_endpoint_bridge", "target": "api_doc_platform_codes", "relation": "references", "confidence": "EXTRACTED", "confidence_score": 1.0, "source_file": "API_DOCUMENTATION.md", "source_location": "line 69", "weight": 1.0}, {"source": "api_doc_endpoint_maprotation", "target": "api_doc_rate_limiting", "relation": "conceptually_related_to", "confidence": "INFERRED", "confidence_score": 0.7, "source_file": "API_DOCUMENTATION.md", "source_location": null, "weight": 0.7}, {"source": "api_doc_proxy_server", "target": "api_doc_client_token", "relation": "implements", "confidence": "EXTRACTED", "confidence_score": 1.0, "source_file": "API_DOCUMENTATION.md", "source_location": "line 11", "weight": 1.0}, {"source": "api_doc_endpoint_servers", "target": "api_doc_attribution_apexlegendsstatus", "relation": "references", "confidence": "EXTRACTED", "confidence_score": 1.0, "source_file": "API_DOCUMENTATION.md", "source_location": "line 442", "weight": 1.0}, {"source": "api_doc_apex_legends_api", "target": "api_doc_error_codes", "relation": "references", "confidence": "EXTRACTED", "confidence_score": 1.0, "source_file": "API_DOCUMENTATION.md", "source_location": "line 609", "weight": 1.0}], "hyperedges": [{"id": "proxy_api_endpoints", "label": "Proxied Apex API Endpoints", "nodes": ["api_doc_proxy_server", "api_doc_endpoint_bridge", "api_doc_endpoint_maprotation", "api_doc_endpoint_servers", "api_doc_endpoint_predator", "api_doc_endpoint_origin", "api_doc_endpoint_nametouid", "api_doc_endpoint_news"], "relation": "implement", "confidence": "EXTRACTED", "confidence_score": 1.0, "source_file": "API_DOCUMENTATION.md"}]}